renux/__init__.py
renux/__main__.py
renux/app.py
renux/assets/styles.tcss
renux/backup.py
renux/bindings.py
renux/cli.py
renux/components/__init__.py
renux/components/form.py
renux/components/preview.py
renux/constants.py
renux/helpers/casing.py
renux/helpers/files.py
renux/helpers/keywords.py
renux/parser.py
renux/py.typed
renux/renamer.py
renux/ui.py
renux-0.1.2.dist-info/LICENSE
renux-0.1.2.dist-info/METADATA
renux-0.1.2.dist-info/WHEEL
renux-0.1.2.dist-info/entry_points.txt
renux-0.1.2.dist-info/RECORD
