Metadata-Version: 2.3
Name: renux
Version: 0.1.2
Summary: A terminal-based bulk file renamer with a TUI
License: MIT
Author: Andrian Lloyd Maagma
Author-email: maagmaandrian@gmail.com
Requires-Python: >=3.10,<4.0.0
Classifier: License :: OSI Approved :: MIT License
Classifier: Programming Language :: Python :: 3
Classifier: Programming Language :: Python :: 3.10
Classifier: Programming Language :: Python :: 3.11
Classifier: Programming Language :: Python :: 3.12
Classifier: Programming Language :: Python :: 3.13
Requires-Dist: python-slugify (>=8.0.4,<9.0.0)
Requires-Dist: rich (>=14.0.0,<15.0.0)
Requires-Dist: textual (>=3.3.0,<4.0.0)
